LICENSE
README.md
setup.py
./ramp/__init__.py
./ramp/data_mgmt/__init__.py
./ramp/data_mgmt/chip_label_pairs.py
./ramp/data_mgmt/clr_callback.py
./ramp/data_mgmt/data_generator.py
./ramp/data_mgmt/display_data.py
./ramp/models/__init__.py
./ramp/models/effunet_1.py
./ramp/models/model_1_chollet_unet.py
./ramp/training/__init__.py
./ramp/training/augmentation_constructors.py
./ramp/training/callback_constructors.py
./ramp/training/loss_constructors.py
./ramp/training/metric_constructors.py
./ramp/training/model_constructors.py
./ramp/training/optimizer_constructors.py
./ramp/utils/__init__.py
./ramp/utils/chip_utils.py
./ramp/utils/eval_utils.py
./ramp/utils/file_utils.py
./ramp/utils/geo_utils.py
./ramp/utils/img_utils.py
./ramp/utils/imgproc_utils.py
./ramp/utils/label_utils.py
./ramp/utils/log_fields.py
./ramp/utils/lrfinder.py
./ramp/utils/mask_to_vec_utils.py
./ramp/utils/misc_ramp_utils.py
./ramp/utils/model_utils.py
./ramp/utils/multimask_utils.py
./ramp/utils/ramp_exceptions.py
./ramp/utils/sdt_mask_utils.py
ramp_fair.egg-info/PKG-INFO
ramp_fair.egg-info/SOURCES.txt
ramp_fair.egg-info/dependency_links.txt
ramp_fair.egg-info/top_level.txt