Metadata-Version: 2.1
Name: ramp-fair
Version: 0.1.2
Summary: Replicable AI for Microplanning , Fork maintained for fAIr
Home-page: 
Author: Carolyn Johnston
Author-email: carolyn.johnston@dev.global
Requires-Python: >=3
License-File: LICENSE
